gliderad2cp/__init__.py
gliderad2cp/_version.py
gliderad2cp/download_example_data.py
gliderad2cp/process_bias.py
gliderad2cp/process_currents.py
gliderad2cp/process_shear.py
gliderad2cp/tools.py
gliderad2cp-0.0.10.dist-info/LICENSE
gliderad2cp-0.0.10.dist-info/METADATA
gliderad2cp-0.0.10.dist-info/WHEEL
gliderad2cp-0.0.10.dist-info/top_level.txt
gliderad2cp-0.0.10.dist-info/RECORD
