Metadata-Version: 2.2
Name: gliderad2cp
Version: 0.0.10
Summary: process glider AD2CP data
Maintainer-email: Callum Rollo <c.rollo@outlook.com>, Bastien Queste <bastien.queste@gu.se>
License: MIT License
Project-URL: documentation, https://github.com/bastienqueste/gliderad2cp
Project-URL: homepage, https://github.com/bastienqueste/gliderad2cp
Project-URL: repository, https://github.com/bastienqueste/gliderad2cp
Classifier: Programming Language :: Python :: 3 :: Only
Classifier: Programming Language :: Python :: 3.8
Classifier: Programming Language :: Python :: 3.9
Classifier: Programming Language :: Python :: 3.10
Classifier: Programming Language :: Python :: 3.11
Classifier: Programming Language :: Python :: 3.12
Requires-Python: >=3.8
License-File: LICENSE
Requires-Dist: dask
Requires-Dist: gsw
Requires-Dist: matplotlib
Requires-Dist: netcdf4
Requires-Dist: numpy
Requires-Dist: pandas
Requires-Dist: pooch
Requires-Dist: pyarrow
Requires-Dist: scipy
Requires-Dist: xarray
